pydict/__init__.py
pydict/decoder.py
pydict/encoder.py
pydict/scanner.py
pydict/tool.py
feaplat-0.0.1.dist-info/LICENSE
feaplat-0.0.1.dist-info/METADATA
feaplat-0.0.1.dist-info/WHEEL
feaplat-0.0.1.dist-info/top_level.txt
feaplat-0.0.1.dist-info/RECORD
