Metadata-Version: 2.1
Name: feaplat
Version: 0.0.1
Summary: Same as json.dumps or json.loads, pydict supprot pydict.dumps and pydict.loads
Home-page: https://github.com/Boris-code/pydict.git
Author: Boris
Author-email: boris_liu@foxmail.com
License: MIT
Platform: UNKNOWN
Classifier: Programming Language :: Python :: 3
Requires-Python: >=3
License-File: LICENSE
